conformer/__init__.py
conformer/common.py
conformer/elements.py
conformer/export.py
conformer/periodic.py
conformer/project.py
conformer/records.py
conformer/registry.yaml
conformer/search.py
conformer/spatial.py
conformer/stages.py
conformer/systems.py
conformer/util.py
conformer/db/__init__.py
conformer/db/models.py
conformer/db/migrations/__init__.py
conformer/db/migrations/migration_20250311_232937.py
conformer/example_systems/181l.pdb
conformer/example_systems/1mmq.pdb
conformer/example_systems/F-water-10-cluster.frag
conformer/example_systems/__init__.py
conformer/example_systems/acetylene.xyz
conformer/example_systems/benzene-6-cluster.xyz
conformer/example_systems/benzene.xyz
conformer/example_systems/charged_protein.pdb
conformer/example_systems/dipeptide.xyz
conformer/example_systems/ethane.xyz
conformer/example_systems/ethanol.xyz
conformer/example_systems/ethene.xyz
conformer/example_systems/formaldehyde.xyz
conformer/example_systems/small_protien.pdb
conformer/example_systems/tetrapeptide.pdb
conformer/example_systems/water-6-cluster.frag
conformer/example_systems/water-6-cluster.xyz
conformer/example_systems/water.xyz
conformer/geometry_readers/__init__.py
conformer/geometry_readers/common.py
conformer/geometry_readers/frag.py
conformer/geometry_readers/pdb.py
conformer/geometry_readers/util.py
conformer/geometry_readers/xyz.py
conformer/mods/MIC.py
conformer/mods/__init__.py
conformer/mods/capping.py
conformer/mods/counterpoise.py
conformer_core/README.md
conformer_core/__init__.py
conformer_core/accessors.py
conformer_core/caching.py
conformer_core/calculation.py
conformer_core/records.py
conformer_core/registry.py
conformer_core/registry.yaml
conformer_core/stages.py
conformer_core/testing.py
conformer_core/util.py
conformer_core/db/__init__.py
conformer_core/db/models.py
conformer_core/db/migrations/__init__.py
conformer_core/db/migrations/__main__.py
conformer_core/db/migrations/migration_20240818_231652.py
conformer_qc-0.3.0.dist-info/METADATA
conformer_qc-0.3.0.dist-info/WHEEL
conformer_qc-0.3.0.dist-info/top_level.txt
conformer_qc-0.3.0.dist-info/RECORD
